context_models/__init__.py
context_models-0.0.1.dist-info/LICENSE
context_models-0.0.1.dist-info/WHEEL
context_models-0.0.1.dist-info/METADATA
context_models-0.0.1.dist-info/RECORD
