Metadata-Version: 2.1
Name: context_models
Version: 0.0.1
Summary: Context models
Author-email: "Blake Naccarato, Kwang Jin Kim" <blake.naccarato@gmail.com>
Requires-Python: >=3.11
Classifier: License :: OSI Approved :: MIT License
Classifier: Programming Language :: Python :: 3.11
Classifier: Programming Language :: Python :: 3.12
Project-URL: Changes, https://softboiler.github.io/context_models/changelog.html
Project-URL: Docs, https://softboiler.github.io/context_models
Project-URL: Home, https://github.com/softboiler/context_models
Project-URL: Tracker, https://github.com/softboiler/context_models/issues
